{
  "videos": [
    {
      "title": "Algebra for Beginners — Full Course",
      "subject": "MATHS",
      "youtube": "LwCRRUa8yTU",
      "duration": "1:08:00"
    },
    {
      "title": "Newton's Laws of Motion — Physics",
      "subject": "PHYSICS",
      "youtube": "kKKM8Y-u7ds",
      "duration": "14:52"
    },
    {
      "title": "Organic Chemistry Introduction",
      "subject": "CHEMISTRY",
      "youtube": "bSMx0NS0XfY",
      "duration": "18:30"
    },
    {
      "title": "English Comprehension Tips and Tricks",
      "subject": "ENGLISH",
      "youtube": "F4Zu5ZZAG7I",
      "duration": "11:45"
    },
    {
      "title": "Cell Biology — Mitosis and Meiosis",
      "subject": "BIOLOGY",
      "youtube": "L0k-enzoeom",
      "duration": "16:20"
    }
  ]
}
